Workbook

Sheet README
A1: CORPORATE BUDGET, FORECAST & PROFITABILITY ANALYSIS
A3: Project Overview
A4: This project simulates the work of a junior Financial Analyst supporting a consumer-products company. The analysis compares monthly budget and actual financial performance, evaluates revenue and profitability variances, develops a simple year-end forecast, and summarizes results in Excel and Power BI.
A7: Objective
A8: Evaluate whether the company is meeting its revenue and profitability targets, identify the largest budget variances, and estimate full-year financial performance.
A11: Skills Demonstrated
A12: Budget vs Actual Analysis
A13: Revenue Analysis
A14: Profitability Analysis
A15: Variance Analysis
A16: Financial Forecasting
A17: Microsoft Excel
... A22: All financial data in this project is synthetic and was created solely for portfolio and educational purposes.

Sheet Monthly Data
A1: MAPLEPEAK CONSUMER PRODUCTS — MONTHLY FINANCIAL DATA
A3: Month | B3: Budget Revenue | C3: Actual Revenue | D3: Budget COGS | E3: Actual COGS | F3: Budget Operating Expenses | G3: Actual Operating Expenses | H3: Budget Gross Profit | I3: Actual Gross Profit | J3: Budget Gross Margin % | K3: Actual Gross Margin % | L3: Budget Operating Profit | M3: Actual Operating Profit | N3: Budget Operating Margin % | O3: Actual Operating Margin % | Q3: Month | R3: Budget Operating Profit | S3: Actual Operating Profit
A4: January | B4: 450000 | C4: 440000 | D4: 270000 | E4: 270000 | F4: 110000 | G4: 112000 | H4: =B4-D4 -> 180000 | I4: =C4-E4 -> 170000 | J4: =H4/B4 -> 0.4 | K4: =I4/C4 -> 0.38636364 | L4: =H4-F4 -> 70000 | M4: =I4-G4 -> 58000 | N4: =L4/B4 -> 0.15555556 | O4: =M4/C4 -> 0.13181818 | Q4: =A4 -> January | R4: =L4 -> 70000 | S4: =M4 -> 58000
A5: February | B5: 460000 | C5: 455000 | D5: 276000 | E5: 280000 | F5: 112000 | G5: 115000 | H5: =B5-D5 -> 184000 | I5: =C5-E5 -> 175000 | J5: =H5/B5 -> 0.4 | K5: =I5/C5 -> 0.38461538 | L5: =H5-F5 -> 72000 | M5: =I5-G5 -> 60000 | N5: =L5/B5 -> 0.15652174 | O5: =M5/C5 -> 0.13186813 | Q5: =A5 -> February | R5: =L5 -> 72000 | S5: =M5 -> 60000
A6: March | B6: 470000 | C6: 462000 | D6: 282000 | E6: 285000 | F6: 114000 | G6: 116000 | H6: =B6-D6 -> 188000 | I6: =C6-E6 -> 177000 | J6: =H6/B6 -> 0.4 | K6: =I6/C6 -> 0.38311688 | L6: =H6-F6 -> 74000 | M6: =I6-G6 -> 61000 | N6: =L6/B6 -> 0.15744681 | O6: =M6/C6 -> 0.13203463 | Q6: =A6 -> March | R6: =L6 -> 74000 | S6: =M6 -> 61000
A7: April | B7: 480000 | C7: 475000 | D7: 288000 | E7: 294000 | F7: 116000 | G7: 119000 | H7: =B7-D7 -> 192000 | I7: =C7-E7 -> 181000 | J7: =H7/B7 -> 0.4 | K7: =I7/C7 -> 0.38105263 | L7: =H7-F7 -> 76000 | M7: =I7-G7 -> 62000 | N7: =L7/B7 -> 0.15833333 | O7: =M7/C7 -> 0.13052632 | Q7: =A7 -> April | R7: =L7 -> 76000 | S7: =M7 -> 62000
A8: May | B8: 500000 | C8: 490000 | D8: 300000 | E8: 305000 | F8: 118000 | G8: 121000 | H8: =B8-D8 -> 200000 | I8: =C8-E8 -> 185000 | J8: =H8/B8 -> 0.4 | K8: =I8/C8 -> 0.37755102 | L8: =H8-F8 -> 82000 | M8: =I8-G8 -> 64000 | N8: =L8/B8 -> 0.164 | O8: =M8/C8 -> 0.13061224 | Q8: =A8 -> May | R8: =L8 -> 82000 | S8: =M8 -> 64000
A9: June | B9: 520000 | C9: 510000 | D9: 312000 | E9: 318000 | F9: 120000 | G9: 123000 | H9: =B9-D9 -> 208000 | I9: =C9-E9 -> 192000 | J9: =H9/B9 -> 0.4 | K9: =I9/C9 -> 0.37647059 | L9: =H9-F9 -> 88000 | M9: =I9-G9 -> 69000 | N9: =L9/B9 -> 0.16923077 | O9: =M9/C9 -> 0.13529412 | Q9: =A9 -> June | R9: =L9 -> 88000 | S9: =M9 -> 69000
A10: July | B10: 540000 | C10: 525000 | D10: 324000 | E10: 325000 | F10: 122000 | G10: 125000 | H10: =B10-D10 -> 216000 | I10: =C10-E10 -> 200000 | J10: =H10/B10 -> 0.4 | K10: =I10/C10 -> 0.38095238 | L10: =H10-F10 -> 94000 | M10: =I10-G10 -> 75000 | N10: =L10/B10 -> 0.17407407 | O10: =M10/C10 -> 0.14285714 | Q10: =A10 -> July | R10: =L10 -> 94000 | S10: =M10 -> 75000
A11: August | B11: 550000 | C11: 540000 | D11: 330000 | E11: 337000 | F11: 124000 | G11: 128000 | H11: =B11-D11 -> 220000 | I11: =C11-E11 -> 203000 | J11: =H11/B11 -> 0.4 | K11: =I11/C11 -> 0.37592593 | L11: =H11-F11 -> 96000 | M11: =I11-G11 -> 75000 | N11: =L11/B11 -> 0.17454545 | O11: =M11/C11 -> 0.13888889 | Q11: =A11 -> August | R11: =L11 -> 96000 | S11: =M11 -> 75000
A12: September | B12: 560000 | D12: 336000 | F12: 126000 | H12: =B12-D12 -> 224000 | J12: =H12/B12 -> 0.4 | L12: =H12-F12 -> 98000 | N12: =L12/B12 -> 0.175
A13: October | B13: 580000 | D13: 348000 | F13: 128000 | H13: =B13-D13 -> 232000 | J13: =H13/B13 -> 0.4 | L13: =H13-F13 -> 104000 | N13: =L13/B13 -> 0.17931034
A14: November | B14: 600000 | D14: 360000 | F14: 130000 | H14: =B14-D14 -> 240000 | J14: =H14/B14 -> 0.4 | L14: =H14-F14 -> 110000 | N14: =L14/B14 -> 0.18333333
A15: December | B15: 650000 | D15: 390000 | F15: 135000 | H15: =B15-D15 -> 260000 | J15: =H15/B15 -> 0.4 | L15: =H15-F15 -> 125000 | N15: =L15/B15 -> 0.19230769

Sheet Variance Analysis 
A1: YTD BUDGET VS ACTUAL ANALYSIS — JANUARY TO AUGUST
A3: Metric | B3: YTD Budget | C3: YTD Actual | D3: Variance $ | E3: Variance % | F3: Interpretation
A4: Revenue | B4: =SUM('Monthly Data'!B4:B11) -> 3970000 | C4: =SUM('Monthly Data'!C4:C11) -> 3897000 | D4: =C4-B4 -> -73000 | E4: =D4/B4 -> -0.018387909 | F4: Unfavourable — Revenue below budget
A5: COGS | B5: =SUM('Monthly Data'!D4:D11) -> 2382000 | C5: =SUM('Monthly Data'!E4:E11) -> 2414000 | D5: =C5-B5 -> 32000 | E5: =D5/B5 -> 0.013434089 | F5: Unfavourable — COGS above budget
A6: Gross Profit | B6: =SUM('Monthly Data'!H4:H11) -> 1588000 | C6: =SUM('Monthly Data'!I4:I11) -> 1483000 | D6: =C6-B6 -> -105000 | E6: =D6/B6 -> -0.066120907 | F6: Unfavourable — Gross profit below budget
A7: Operating Expenses | B7: =SUM('Monthly Data'!F4:F11) -> 936000 | C7: =SUM('Monthly Data'!G4:G11) -> 959000 | D7: =C7-B7 -> 23000 | E7: =D7/B7 -> 0.02457265 | F7: Unfavourable — Operating expenses above budget
A8: Operating Profit | B8: =SUM('Monthly Data'!L4:L11) -> 652000 | C8: =SUM('Monthly Data'!M4:M11) -> 524000 | D8: =C8-B8 -> -128000 | E8: =D8/B8 -> -0.19631902 | F8: Unfavourable — Operating profit below budget

Sheet Forecast
A1: FULL-YEAR FINANCIAL FORECAST
A3: Metric | B3: YTD Budget | C3: YTD Actual | D3: YTD Actual / Budget | E3: Remaining Budget | F3: Forecast Remaining | G3: Full-Year Budget | H3: Full-Year Forecast | I3: Forecast Variance $ | J3: Forecast Variance %
A4: Revenue | B4: ='Variance Analysis '!B4 -> 3970000 | C4: ='Variance Analysis '!C4 -> 3897000 | D4: =C4/B4 -> 0.98161209 | E4: =SUM('Monthly Data'!B12:B15) -> 2390000 | F4: =E4*D4 -> 2346052.9 | G4: =SUM('Monthly Data'!B4:B15) -> 6360000 | H4: =C4+F4 -> 6243052.9 | I4: =H4-G4 -> -116947.1 | J4: =I4/G4 -> -0.018387909
A5: COGS | B5: ='Variance Analysis '!B5 -> 2382000 | C5: ='Variance Analysis '!C5 -> 2414000 | D5: =C5/B5 -> 1.0134341 | E5: =SUM('Monthly Data'!D12:D15) -> 1434000 | F5: =E5*D5 -> 1453264.5 | G5: =SUM('Monthly Data'!D4:D15) -> 3816000 | H5: =C5+F5 -> 3867264.5 | I5: =H5-G5 -> 51264.484 | J5: =I5/G5 -> 0.013434089
A6: Operating Expenses | B6: ='Variance Analysis '!B7 -> 936000 | C6: ='Variance Analysis '!C7 -> 959000 | D6: =C6/B6 -> 1.0245726 | E6: =SUM('Monthly Data'!F12:F15) -> 519000 | F6: =E6*D6 -> 531753.21 | G6: =SUM('Monthly Data'!F4:F15) -> 1455000 | H6: =C6+F6 -> 1490753.2 | I6: =H6-G6 -> 35753.205 | J6: =I6/G6 -> 0.02457265
A7: Gross Profit | B7: ='Variance Analysis '!B6 -> 1588000 | C7: ='Variance Analysis '!C6 -> 1483000 | D7: =C7/B7 -> 0.93387909 | E7: =E4-E5 -> 956000 | F7: =F4-F5 -> 892788.41 | G7: =G4-G5 -> 2544000 | H7: =H4-H5 -> 2375788.4 | I7: =H7-G7 -> -168211.59 | J7: =I7/G7 -> -0.066120907
A8: Operating Profit | B8: ='Variance Analysis '!B8 -> 652000 | C8: ='Variance Analysis '!C8 -> 524000 | D8: =C8/B8 -> 0.80368098 | E8: =E7-E6 -> 437000 | F8: =F7-F6 -> 361035.21 | G8: =G7-G6 -> 1089000 | H8: =H7-H6 -> 885035.21 | I8: =H8-G8 -> -203964.79 | J8: =I8/G8 -> -0.18729549

Sheet Dashboard
A1: CORPORATE BUDGET, FORECAST & PROFITABILITY DASHBOARD
A3: FULL-YEAR BUDGET REVENUE | C3: FULL-YEAR FORECAST REVENUE | E3: BUDGET OPERATING PROFIT | G3: FORECAST OPERATING PROFIT
A4: =Forecast!G4 -> 6360000 | C4: =Forecast!H4 -> 6243052.9 | E4: =Forecast!G8 -> 1089000 | G4: =Forecast!H8 -> 885035.21
A7: REVENUE FORECAST VARIANCE % | C7: OPERATING PROFIT FORECAST VARIANCE %
A8: =Forecast!J4 -> -0.018387909 | C8: =Forecast!J8 -> -0.18729549
